README.rst
setup.cfg
setup.py
staticmaps_signature/__init__.py
staticmaps_signature/signature.py
staticmaps_signature.egg-info/PKG-INFO
staticmaps_signature.egg-info/SOURCES.txt
staticmaps_signature.egg-info/dependency_links.txt
staticmaps_signature.egg-info/not-zip-safe
staticmaps_signature.egg-info/requires.txt
staticmaps_signature.egg-info/top_level.txt
tests/__init__.py
tests/conftest.py
tests/test_signature.py