Metadata-Version: 1.0
Name: staticmaps-signature
Version: 0.2.0
Summary: Easily sign Google StaticMap API request urls with your API Key or Client ID
Home-page: https://github.com/allrod5/staticmaps-signature/
Author: Rodrigo Martins de Oliveira
Author-email: allrod5@hotmail.com
License: MIT
Platform: any
